dictionary/__init__.py
dictionary/dictionary.py
cagri_durgut_cs453-2.0.0.dist-info/METADATA
cagri_durgut_cs453-2.0.0.dist-info/WHEEL
cagri_durgut_cs453-2.0.0.dist-info/top_level.txt
cagri_durgut_cs453-2.0.0.dist-info/RECORD
