Metadata-Version: 2.1
Name: cagri-durgut-cs453
Version: 2.0.0
Summary: UNKNOWN
Author: Çağrı Durgut
License: UNKNOWN
Platform: UNKNOWN
Requires-Python: >=3.8
Requires-Dist: requests (>=2.23.0)
